AUTHORS.rst
CHANGES.rst
HGREV
LICENSE.txt
MANIFEST.in
README.rst
setup.py
django_form_utils.egg-info/PKG-INFO
django_form_utils.egg-info/SOURCES.txt
django_form_utils.egg-info/dependency_links.txt
django_form_utils.egg-info/not-zip-safe
django_form_utils.egg-info/top_level.txt
form_utils/__init__.py
form_utils/admin.py
form_utils/fields.py
form_utils/forms.py
form_utils/models.py
form_utils/settings.py
form_utils/utils.py
form_utils/widgets.py
form_utils/media/form_utils/js/autoresize.js
form_utils/media/form_utils/js/jquery.autogrow.js
form_utils/templates/form_utils/better_form.html
form_utils/templates/form_utils/fields_as_lis.html
form_utils/templates/form_utils/form.html
form_utils/templates/forms/_label.html
form_utils/templatetags/__init__.py
form_utils/templatetags/form_utils.py