Metadata-Version: 1.1
Name: django-form-utils
Version: 0.3
Summary: Form utilities for Django
Home-page: http://bitbucket.org/carljm/django-form-utils/
Author: Carl Meyer
Author-email: carl@dirtcircle.com
License: UNKNOWN
Platform: UNKNOWN
Classifier: Development Status :: 4 - Beta
Classifier: Environment :: Web Environment
Classifier: Intended Audience :: Developers
Classifier: License :: OSI Approved :: BSD License
Classifier: Operating System :: OS Independent
Classifier: Programming Language :: Python
Classifier: Framework :: Django
